multimodal_analyzer_cli/__init__.py
multimodal_analyzer_cli/audio_analyzer.py
multimodal_analyzer_cli/cli.py
multimodal_analyzer_cli/config.py
multimodal_analyzer_cli/image_analyzer.py
multimodal_analyzer_cli/video_analyzer.py
multimodal_analyzer_cli/auth/__init__.py
multimodal_analyzer_cli/auth/google_auth.py
multimodal_analyzer_cli/auth/oauth_manager.py
multimodal_analyzer_cli/auth/token_storage.py
multimodal_analyzer_cli/models/__init__.py
multimodal_analyzer_cli/models/litellm_model.py
multimodal_analyzer_cli/prompts/audio_system_prompt.md
multimodal_analyzer_cli/prompts/image_system_prompt.md
multimodal_analyzer_cli/prompts/video_system_prompt.md
multimodal_analyzer_cli/utils/__init__.py
multimodal_analyzer_cli/utils/audio.py
multimodal_analyzer_cli/utils/file_discovery.py
multimodal_analyzer_cli/utils/image.py
multimodal_analyzer_cli/utils/output.py
multimodal_analyzer_cli/utils/prompts.py
multimodal_analyzer_cli/utils/streaming.py
multimodal_analyzer_cli/utils/video.py
multimodal_analyzer-0.1.0.dist-info/METADATA
multimodal_analyzer-0.1.0.dist-info/WHEEL
multimodal_analyzer-0.1.0.dist-info/entry_points.txt
multimodal_analyzer-0.1.0.dist-info/RECORD
