Metadata-Version: 2.4
Name: multimodal-analyzer
Version: 0.1.0
Summary: AI-powered media analysis tool for images, audio, and video using multiple LLM providers
Classifier: Development Status :: 4 - Beta
Classifier: Intended Audience :: Developers
Classifier: License :: OSI Approved :: MIT License
Classifier: Programming Language :: Python :: 3
Classifier: Programming Language :: Python :: 3.12
Requires-Python: >=3.12
Requires-Dist: aiofiles>=24.0.0
Requires-Dist: click>=8.1.0
Requires-Dist: diskcache>=5.6.3
Requires-Dist: ffmpeg-python>=0.2.0
Requires-Dist: google-auth-oauthlib>=1.0.0
Requires-Dist: google-auth>=2.0.0
Requires-Dist: litellm>=1.72.2
Requires-Dist: loguru>=0.7.2
Requires-Dist: nest-asyncio>=1.6.0
Requires-Dist: numpy>=2.3.2
Requires-Dist: openai<1.99.0,>=1.35.0
Requires-Dist: pillow>=10.0.0
Requires-Dist: pydub>=0.25.0
Requires-Dist: pytest-asyncio>=1.0.0
Requires-Dist: pytest-cov>=6.2.1
Requires-Dist: pytest>=8.4.1
Requires-Dist: python-dotenv>=1.0.0
Requires-Dist: pyyaml>=6.0.0
Requires-Dist: requests>=2.28.0
Requires-Dist: rich>=13.0.0
Requires-Dist: tenacity>=8.0.0
Requires-Dist: tqdm>=4.66.0
